jsl_django_sitemap/__init__.py
jsl_django_sitemap/apps.py
jsl_django_sitemap/default_settings.py
jsl_django_sitemap/jsl_sitemap_utils.py
jsl_django_sitemap/models.py
jsl_django_sitemap/tests.py
jsl_django_sitemap/views.py
jsl_django_sitemap/migrations/__init__.py
jsl_django_sitemap-1.2.4.dist-info/LICENSE
jsl_django_sitemap-1.2.4.dist-info/METADATA
jsl_django_sitemap-1.2.4.dist-info/WHEEL
jsl_django_sitemap-1.2.4.dist-info/top_level.txt
jsl_django_sitemap-1.2.4.dist-info/RECORD
