Metadata-Version: 2.1
Name: jsl-django-sitemap
Version: 1.2.4
Summary: JSL Django Sitemap is a Django utility which iterates over all the url patterns in your main Django project and creates a ready to use sitemap. The sitemap.xml is useful in crawlers such as Google, Bing, Yahoo. We hope you like our app! Leave a star on our GitHub repository. Thanks!
Home-page: https://github.com/JSoftwareLabs/jsl_django_sitemap
Download-URL: https://github.com/JSoftwareLabs/jsl_django_sitemap/archive/refs/tags/1.2.4.tar.gz
Author: JSoftwareLabs.com
Author-email: info@jsoftwarelabs.com
License: MIT
Keywords: Django sitemap,JSoftwareLabs,sitemap.xml,Django automated sitemaps
Classifier: Development Status :: 5 - Production/Stable
Classifier: Intended Audience :: Developers
Classifier: Topic :: Software Development :: Build Tools
Classifier: License :: OSI Approved :: Apache Software License
Classifier: Programming Language :: Python :: 3.5
Classifier: Programming Language :: Python :: 3.6
Classifier: Programming Language :: Python :: 3.7
Classifier: Programming Language :: Python :: 3.8
Classifier: Programming Language :: Python :: 3.9
License-File: LICENSE
Requires-Dist: Django (>=2.2)
